{"name":"Ditib-tools","tagline":"","body":"ditib-tools\r\n===========\r\nSome Java classes to parse and persist DITIB data with Spring\r\n\r\n\r\nStatus\r\n======\r\n[![Dependency Status](https://www.versioneye.com/user/projects/53de9ae116279fb98c000007/badge.svg?style=flat)](https://www.versioneye.com/user/projects/53de9ae116279fb98c000007)\r\n\r\nMaven site(s)\r\n=============\r\n* [SNAPSHOT](http://hakan42.github.io/ditib-tools/site/0.0.1-SNAPSHOT/)\r\n","google":"","note":"Don't delete this file! It's used internally to help with page regeneration."}